masecret/__init__.py
masecret/builders.py
masecret/cli.py
masecret/position_utils.py
masecret-0.4.0.dist-info/LICENSE
masecret-0.4.0.dist-info/METADATA
masecret-0.4.0.dist-info/WHEEL
masecret-0.4.0.dist-info/entry_points.txt
masecret-0.4.0.dist-info/top_level.txt
masecret-0.4.0.dist-info/RECORD
