Metadata-Version: 2.1
Name: masecret
Version: 0.4.0
Summary: A command to mask secret information of images using OCR
Home-page: https://github.com/orangain/masecret
Author: orangain
Author-email: orangain@gmail.com
License: MIT
Keywords: ocr image screenshot secret mask
Platform: UNKNOWN
Classifier: Development Status :: 4 - Beta
Classifier: Environment :: Console
Classifier: License :: OSI Approved :: MIT License
Classifier: Programming Language :: Python :: 3.3
Classifier: Programming Language :: Python :: 3.4
Classifier: Programming Language :: Python :: 3.5
Classifier: Programming Language :: Python :: 3.6
Classifier: Programming Language :: Python :: 3.7
Classifier: Programming Language :: Python :: 3 :: Only
Classifier: Topic :: Utilities
Requires-Dist: Pillow
Requires-Dist: pyocr (>=0.5.3)
